rdflib_jsonld/__init__.py
rdflib_jsonld/_compat.py
rdflib_jsonld/context.py
rdflib_jsonld/errors.py
rdflib_jsonld/keys.py
rdflib_jsonld/parser.py
rdflib_jsonld/serializer.py
rdflib_jsonld/util.py
rdflib_jsonld_without_2to3-0.7.0.dist-info/LICENSE.md
rdflib_jsonld_without_2to3-0.7.0.dist-info/METADATA
rdflib_jsonld_without_2to3-0.7.0.dist-info/WHEEL
rdflib_jsonld_without_2to3-0.7.0.dist-info/entry_points.txt
rdflib_jsonld_without_2to3-0.7.0.dist-info/top_level.txt
rdflib_jsonld_without_2to3-0.7.0.dist-info/RECORD
