Metadata-Version: 2.1
Name: rdflib-jsonld-without-2to3
Version: 0.7.0
Summary: rdflib extension adding JSON-LD parser and serializer (without 2to3)
Home-page: https://github.com/logilab/rdflib-jsonld-without-2to3
Maintainer: None
Maintainer-email: none@notmaintained.logilab.fr
License: BSD
Platform: any
Classifier: Programming Language :: Python
Classifier: Programming Language :: Python :: 3
Classifier: Programming Language :: Python :: 3.6
Classifier: Programming Language :: Python :: 3.7
Classifier: Programming Language :: Python :: 3.8
Classifier: Programming Language :: Python :: 3.9
Classifier: License :: OSI Approved :: BSD License
Classifier: Topic :: Software Development :: Libraries :: Python Modules
Classifier: Operating System :: OS Independent
Classifier: Natural Language :: English
Requires-Dist: rdflib
